mearul-0.1.dist-info/licenses/LICENSE.txt
mearul_package/__init__.py
mearul_package/helpers.py
mearul-0.1.dist-info/METADATA
mearul-0.1.dist-info/WHEEL
mearul-0.1.dist-info/top_level.txt
mearul-0.1.dist-info/RECORD
