Metadata-Version: 2.4
Name: mearul
Version: 0.1
Summary: Fully hidden Python package for Jupyter Notebook
Home-page: https://github.com/yourgithub/mearul_package_final
Author: Justin
Author-email: me@dev.org
Classifier: Programming Language :: Python :: 3
Classifier: License :: OSI Approved :: MIT License
Classifier: Operating System :: OS Independent
Requires-Python: >=3.8
License-File: LICENSE.txt
Requires-Dist: cryptography
Dynamic: author
Dynamic: author-email
Dynamic: classifier
Dynamic: home-page
Dynamic: license-file
Dynamic: requires-dist
Dynamic: requires-python
Dynamic: summary
